wingwalker/__init__.py
wingwalker/base.py
wingwalker/lednicer.py
wingwalker/output_templates.py
wingwalker/selig.py
wingwalker/svg.py
wingwalker/utils.py
wingwalker/build_params/__init__.py
wingwalker/build_params/wing_request.py
wingwalker/generators/__init__.py
wingwalker/generators/elliptical.py
wingwalker/generators/geometric.py
wingwalker/generators/iterators.py
wingwalker/generators/rectangular.py
wingwalker/generators/wing.py
wingwalker/io/__init__.py
wingwalker/io/exports.py
wingwalker/io/specs.py
wingwalker/models/__init__.py
wingwalker/models/airfoil_section.py
wingwalker/models/airfoil_specs.py
wingwalker/models/enums.py
wingwalker/models/wing_model.py
wingwalker/processing/__init__.py
wingwalker/processing/mesh.py
wingwalker/templates/svg.tpl
wingwalker/data/lednicer_nasasc2-0714-il.dat
wingwalker/data/lednicer_supercritical_nasa-sc2-1010.dat
wingwalker/data/lednicer_symmetrical_n0011sc-il.dat
wingwalker/data/lednicerdatfile.txt
wingwalker/data/selig_naca2412.dat
wingwalker/data/selig_nasasc2-0714-il.dat
wingwalker/data/selig_supercritical_nasa-sc2-1010.dat
wingwalker/data/selig_symmetrical_n0011sc-il.dat
wingwalker/data/seligdatfile.txt
wingwalker-1.1.0.dist-info/METADATA
wingwalker-1.1.0.dist-info/WHEEL
wingwalker-1.1.0.dist-info/licenses/LICENSE
wingwalker-1.1.0.dist-info/RECORD
