Metadata-Version: 2.4
Name: wingwalker
Version: 1.1.0
Summary: Wingwalker Airfoil and Wing Design Tools'
Project-URL: Homepage, https://github.com/david-days/wingwalker-pypi
Project-URL: Issues, https://github.com/david-days/wingwalker-pypi
Author-email: David Days <david.c.days@gmail.com>
License-Expression: MIT
License-File: LICENSE
Classifier: Operating System :: OS Independent
Classifier: Programming Language :: Python :: 3
Requires-Python: >=3.11
Requires-Dist: numpy
Requires-Dist: pymeshlab
Requires-Dist: pyvista
Requires-Dist: shapely
Requires-Dist: typer
Requires-Dist: typing-extensions
